bittrade/__init__.py
bittrade/__main__.py
bittrade/cli.py
bittrade/data/__init__.py
bittrade/data/google_client.py
bittrade-0.1.1.dist-info/DESCRIPTION.rst
bittrade-0.1.1.dist-info/METADATA
bittrade-0.1.1.dist-info/RECORD
bittrade-0.1.1.dist-info/WHEEL
bittrade-0.1.1.dist-info/entry_points.txt
bittrade-0.1.1.dist-info/metadata.json
bittrade-0.1.1.dist-info/top_level.txt
