Metadata-Version: 2.0
Name: bittrade
Version: 0.1.1
Summary: Crypto trading AI agent.
Home-page: https://github.com/JunhaoWang/bittrade
Author: Junhao Wang
Author-email: junhao@umich.edu
License: MIT license
Keywords: crpto,ai
Platform: UNKNOWN
Classifier: Development Status :: 5 - Production/Stable
Classifier: Intended Audience :: Developers
Classifier: License :: OSI Approved :: MIT License
Classifier: Operating System :: Unix
Classifier: Operating System :: POSIX
Classifier: Operating System :: Microsoft :: Windows
Classifier: Programming Language :: Python :: 3.6
Classifier: Topic :: Utilities
Requires-Dist: click
Requires-Dist: pandas
Requires-Dist: requests
